criminalip/__init__.py
criminalip/api.py
criminalip/crimial_ip.py
criminalip/version.py
tests/__init__.py
tests/test_CriminalIP.py
PyCriminalIP-0.2.0.dist-info/LICENSE
PyCriminalIP-0.2.0.dist-info/METADATA
PyCriminalIP-0.2.0.dist-info/WHEEL
PyCriminalIP-0.2.0.dist-info/top_level.txt
PyCriminalIP-0.2.0.dist-info/RECORD
