Metadata-Version: 2.1
Name: PyCriminalIP
Version: 0.2.0
Summary: Python library for CriminalIP(https://www.criminalip.io/)
Home-page: https://github.com/haginara/PyCriminalIP
Author: Jonghak Choi
Author-email: haginara@gmail.com
License: MIT License
Classifier: License :: OSI Approved :: MIT License
Classifier: Programming Language :: Python
Classifier: Programming Language :: Python :: 3
Classifier: Programming Language :: Python :: 3.11
License-File: LICENSE
Requires-Dist: requests
